selfie/__init__.py
selfie/__version__.py
selfie-0.3.1.data/scripts/selfie
selfie-0.3.1.dist-info/METADATA
selfie-0.3.1.dist-info/WHEEL
selfie-0.3.1.dist-info/top_level.txt
selfie-0.3.1.dist-info/RECORD
