Metadata-Version: 2.1
Name: selfie
Version: 0.3.1
Summary: Dump environment to JSON file before executing a command
Home-page: https://github.com/harvard-nrg/selfie
Author: Neuroinformatics Research Group
Author-email: info@neuroinfo.org
